emlib/__init__.py
emlib/_dialogsqt.py
emlib/_dialogsqt6.py
emlib/calculus.py
emlib/classproperty.py
emlib/colordata.py
emlib/combinatorics.py
emlib/common.py
emlib/containers.py
emlib/csvtools.py
emlib/dialogs.py
emlib/doctools.py
emlib/electronics.py
emlib/envir.py
emlib/filetools.py
emlib/graphlib.py
emlib/img.py
emlib/iterlib.py
emlib/jsontools.py
emlib/logutils.py
emlib/mathlib.py
emlib/matplotting.py
emlib/misc.py
emlib/net.py
emlib/numberseries.py
emlib/numpytools.py
emlib/numtheory.py
emlib/parabolicinterpol.py
emlib/py.typed
emlib/readbytes.py
emlib/result.py
emlib/shelling.py
emlib/smooth.py
emlib/stochastic.py
emlib/textlib.py
emlib/video.py
emlib/xmlprinter.py
emlib-1.20.2.dist-info/licenses/LICENSE.md
emlib-1.20.2.dist-info/METADATA
emlib-1.20.2.dist-info/WHEEL
emlib-1.20.2.dist-info/top_level.txt
emlib-1.20.2.dist-info/RECORD
