Metadata-Version: 2.4
Name: emlib
Version: 1.20.2
Summary: Miscellaneous utilities (text handling, maths, iterators, etc.)
Author-email: Eduardo Moguillansky <eduardo.moguillansky@gmail.com>
Project-URL: Homepage, https://github.com/gesellkammer/emlib
Classifier: Programming Language :: Python :: 3
Classifier: Operating System :: OS Independent
Requires-Python: >=3.10
License-File: LICENSE.md
Requires-Dist: numpy
Requires-Dist: appdirs
Requires-Dist: tabulate
Requires-Dist: watchdog
Requires-Dist: matplotlib
Requires-Dist: pillow<11
Requires-Dist: decorator
Requires-Dist: ttkthemes
Dynamic: license-file
